{"options":{"validator":{"$jsonSchema":{"bsonType":"object","required":["event_type","station_id","timestamp"],"properties":{"event_type":{"enum":["STATION_STATUS_CHANGE","CONNECTOR_STATUS_CHANGE","SESSION_START","SESSION_END","MAINTENANCE_START","MAINTENANCE_END"]},"station_id":{"bsonType":"string"},"timestamp":{"bsonType":"date"},"old_status":{"bsonType":"string"},"new_status":{"bsonType":"string"},"connector_id":{"bsonType":"string"},"event_data":{"bsonType":"object","properties":{"session_ended":{"bsonType":"bool"},"session_duration_minutes":{"bsonType":"int","minimum":{"$numberInt":"0"}},"energy_delivered_kwh":{"bsonType":"double","minimum":{"$numberInt":"0"}}}},"processed":{"bsonType":"bool"},"processing_batch":{"bsonType":"string"}}}}},"indexes":[{"v":{"$numberInt":"2"},"key":{"_id":{"$numberInt":"1"}},"name":"_id_"},{"v":{"$numberInt":"2"},"key":{"processed":{"$numberInt":"1"},"timestamp":{"$numberInt":"1"}},"name":"processed_1_timestamp_1"}],"uuid":"61b7417f352f449a8b5af7a27184c86a","collectionName":"events","type":"collection"}